[
  {
    "ticker": "AAPL",
    "name": "Apple",
    "rating": "Strong Buy",
    "score": 0.625,
    "change_pct": -0.66,
    "price": 315.2,
    "currency": "$",
    "favorite": true,
    "trend": "Uptrend",
    "rsi": 61.82,
    "as_of": "2026-07-14T23:36:57+05:30",
    "one_liner": "Price is above both its 50- and 200-day averages (a healthy uptrend)"
  },
  {
    "ticker": "NVDA",
    "name": "Nvidia",
    "rating": "Strong Buy",
    "score": 0.625,
    "change_pct": 3.79,
    "price": 211.24,
    "currency": "$",
    "favorite": true,
    "trend": "Uptrend",
    "rsi": 56.0,
    "as_of": "2026-07-14T23:36:58+05:30",
    "one_liner": "Price is above both its 50- and 200-day averages (a healthy uptrend)"
  },
  {
    "ticker": "BTC-USD",
    "name": "Bitcoin",
    "rating": "Neutral",
    "score": 0.125,
    "change_pct": 3.67,
    "price": 64520.48,
    "currency": "$",
    "favorite": true,
    "trend": "Sideways",
    "rsi": 54.79,
    "as_of": "2026-07-14T23:37:04+05:30",
    "one_liner": "Price is between its 50- and 200-day averages (mixed / transitional)"
  },
  {
    "ticker": "RELIANCE.NS",
    "name": "Reliance Industries",
    "rating": "Strong Sell",
    "score": -0.625,
    "change_pct": -0.3,
    "price": 1293.0,
    "currency": "\u20b9",
    "favorite": true,
    "trend": "Downtrend",
    "rsi": 45.36,
    "as_of": "2026-07-14T23:37:02+05:30",
    "one_liner": "Price is below both its 50- and 200-day averages (a downtrend)"
  },
  {
    "ticker": "AMD",
    "name": "Advanced Micro Devices, Inc.",
    "rating": "Strong Buy",
    "score": 0.625,
    "change_pct": -6.89,
    "price": 540.88,
    "currency": "$",
    "favorite": false,
    "trend": "Uptrend",
    "rsi": 56.48,
    "as_of": "2026-07-02T12:32:53+05:30",
    "one_liner": "is rated **Strong Buy** on the technical suite"
  },
  {
    "ticker": "^GSPC",
    "name": "S&P 500",
    "rating": "Strong Buy",
    "score": 0.625,
    "change_pct": 0.46,
    "price": 7549.7,
    "currency": "$",
    "favorite": false,
    "trend": "Uptrend",
    "rsi": 56.92,
    "as_of": "2026-07-14T23:36:54+05:30",
    "one_liner": "Price is above both its 50- and 200-day averages (a healthy uptrend)"
  },
  {
    "ticker": "^IXIC",
    "name": "Nasdaq Composite",
    "rating": "Strong Buy",
    "score": 0.625,
    "change_pct": 1.07,
    "price": 26151.11,
    "currency": "$",
    "favorite": false,
    "trend": "Uptrend",
    "rsi": 52.51,
    "as_of": "2026-07-14T23:36:55+05:30",
    "one_liner": "Price is above both its 50- and 200-day averages (a healthy uptrend)"
  },
  {
    "ticker": "INR=X",
    "name": "USD/INR",
    "rating": "Strong Buy",
    "score": 0.562,
    "change_pct": 0.91,
    "price": 96.19,
    "currency": "$",
    "favorite": false,
    "trend": "Uptrend",
    "rsi": 60.32,
    "as_of": "2026-07-14T23:37:07+05:30",
    "one_liner": "Price is above both its 50- and 200-day averages (a healthy uptrend)"
  },
  {
    "ticker": "AMZN",
    "name": "Amazon",
    "rating": "Strong Buy",
    "score": 0.5,
    "change_pct": -0.32,
    "price": 246.53,
    "currency": "$",
    "favorite": false,
    "trend": "Sideways",
    "rsi": 52.02,
    "as_of": "2026-07-14T23:36:59+05:30",
    "one_liner": "Price is between its 50- and 200-day averages (mixed / transitional)"
  },
  {
    "ticker": "^DJI",
    "name": "Dow Jones",
    "rating": "Strong Buy",
    "score": 0.5,
    "change_pct": -0.05,
    "price": 52471.72,
    "currency": "$",
    "favorite": false,
    "trend": "Uptrend",
    "rsi": 59.27,
    "as_of": "2026-07-14T23:36:55+05:30",
    "one_liner": "Price is above both its 50- and 200-day averages (a healthy uptrend)"
  },
  {
    "ticker": "ETH-USD",
    "name": "Ethereum",
    "rating": "Buy",
    "score": 0.25,
    "change_pct": 5.42,
    "price": 1869.56,
    "currency": "$",
    "favorite": false,
    "trend": "Sideways",
    "rsi": 63.06,
    "as_of": "2026-07-14T23:37:05+05:30",
    "one_liner": "Price is between its 50- and 200-day averages (mixed / transitional)"
  },
  {
    "ticker": "HDFCBANK.NS",
    "name": "HDFC Bank",
    "rating": "Buy",
    "score": 0.25,
    "change_pct": -1.05,
    "price": 809.4,
    "currency": "\u20b9",
    "favorite": false,
    "trend": "Sideways",
    "rsi": 55.73,
    "as_of": "2026-07-14T23:37:03+05:30",
    "one_liner": "Price is between its 50- and 200-day averages (mixed / transitional)"
  },
  {
    "ticker": "CL=F",
    "name": "Crude Oil (WTI)",
    "rating": "Neutral",
    "score": 0.125,
    "change_pct": 0.73,
    "price": 78.71,
    "currency": "$",
    "favorite": false,
    "trend": "Sideways",
    "rsi": 52.19,
    "as_of": "2026-07-14T23:37:06+05:30",
    "one_liner": "Price is between its 50- and 200-day averages (mixed / transitional)"
  },
  {
    "ticker": "^NSEBANK",
    "name": "Bank Nifty",
    "rating": "Neutral",
    "score": 0.125,
    "change_pct": -1.15,
    "price": 57462.3,
    "currency": "$",
    "favorite": false,
    "trend": "Sideways",
    "rsi": 52.83,
    "as_of": "2026-07-14T23:37:01+05:30",
    "one_liner": "Price is above both its 50- and 200-day averages (a healthy uptrend)"
  },
  {
    "ticker": "GOOGL",
    "name": "Alphabet",
    "rating": "Neutral",
    "score": 0.0,
    "change_pct": 1.49,
    "price": 357.74,
    "currency": "$",
    "favorite": false,
    "trend": "Sideways",
    "rsi": 48.05,
    "as_of": "2026-07-14T23:36:58+05:30",
    "one_liner": "Price is between its 50- and 200-day averages (mixed / transitional)"
  },
  {
    "ticker": "meta",
    "name": "Meta Platforms, Inc.",
    "rating": "Neutral",
    "score": 0.0,
    "change_pct": -4.9,
    "price": 582.9,
    "currency": "$",
    "favorite": false,
    "trend": "Downtrend",
    "rsi": 49.6,
    "as_of": "2026-07-05T14:31:17+05:30",
    "one_liner": "is rated **Neutral** on the technical suite"
  },
  {
    "ticker": "TCS.NS",
    "name": "TCS",
    "rating": "Neutral",
    "score": 0.0,
    "change_pct": 0.88,
    "price": 2200.6,
    "currency": "\u20b9",
    "favorite": false,
    "trend": "Downtrend",
    "rsi": 56.56,
    "as_of": "2026-07-14T23:37:02+05:30",
    "one_liner": "Price is below both its 50- and 200-day averages (a downtrend)"
  },
  {
    "ticker": "^BSESN",
    "name": "Sensex",
    "rating": "Neutral",
    "score": 0.0,
    "change_pct": -0.72,
    "price": 77054.94,
    "currency": "$",
    "favorite": false,
    "trend": "Sideways",
    "rsi": 52.21,
    "as_of": "2026-07-14T23:37:01+05:30",
    "one_liner": "Price is between its 50- and 200-day averages (mixed / transitional)"
  },
  {
    "ticker": "^NSEI",
    "name": "Nifty 50",
    "rating": "Neutral",
    "score": 0.0,
    "change_pct": -0.66,
    "price": 24052.05,
    "currency": "$",
    "favorite": false,
    "trend": "Sideways",
    "rsi": 51.67,
    "as_of": "2026-07-14T23:37:00+05:30",
    "one_liner": "Price is between its 50- and 200-day averages (mixed / transitional)"
  },
  {
    "ticker": "INFY.NS",
    "name": "Infosys",
    "rating": "Neutral",
    "score": -0.125,
    "change_pct": -0.88,
    "price": 1092.9,
    "currency": "\u20b9",
    "favorite": false,
    "trend": "Downtrend",
    "rsi": 51.43,
    "as_of": "2026-07-14T23:37:04+05:30",
    "one_liner": "Price is below both its 50- and 200-day averages (a downtrend)"
  },
  {
    "ticker": "MSFT",
    "name": "Microsoft",
    "rating": "Neutral",
    "score": -0.125,
    "change_pct": -0.91,
    "price": 387.43,
    "currency": "$",
    "favorite": false,
    "trend": "Downtrend",
    "rsi": 48.88,
    "as_of": "2026-07-14T23:36:57+05:30",
    "one_liner": "Price is below both its 50- and 200-day averages (a downtrend)"
  },
  {
    "ticker": "GC=F",
    "name": "Gold",
    "rating": "Strong Sell",
    "score": -0.5,
    "change_pct": 1.84,
    "price": 4070.5,
    "currency": "$",
    "favorite": false,
    "trend": "Downtrend",
    "rsi": 42.6,
    "as_of": "2026-07-14T23:37:05+05:30",
    "one_liner": "Price is below both its 50- and 200-day averages (a downtrend)"
  },
  {
    "ticker": "^VIX",
    "name": "VIX (volatility)",
    "rating": "Strong Sell",
    "score": -0.625,
    "change_pct": -3.96,
    "price": 16.48,
    "currency": "$",
    "favorite": false,
    "trend": "Downtrend",
    "rsi": 47.73,
    "as_of": "2026-07-14T23:36:56+05:30",
    "one_liner": "Price is below both its 50- and 200-day averages (a downtrend)"
  },
  {
    "ticker": "TSLA",
    "name": "Tesla",
    "rating": "Strong Sell",
    "score": -0.75,
    "change_pct": 0.5,
    "price": 396.74,
    "currency": "$",
    "favorite": false,
    "trend": "Downtrend",
    "rsi": 47.89,
    "as_of": "2026-07-14T23:37:00+05:30",
    "one_liner": "Price is below both its 50- and 200-day averages (a downtrend)"
  }
]